{"date":"2022-04-18","results":[{"title":"Q1","sql":"SELECT DayOfWeek, count(*) AS c FROM default.ontime WHERE Year \u003e= 2000 AND Year \u003c= 2008 GROUP BY DayOfWeek ORDER BY c DESC;","lines":[0.143,0.224,0.147,0.15752346420373303],"version":"v0.7.21-nightly","xAxis":["min","max","median","mean"]},{"title":"Q2","sql":"SELECT DayOfWeek, count(*) AS c FROM default.ontime WHERE DepDelay\u003e10 AND Year \u003e= 2000 AND Year \u003c= 2008 GROUP BY DayOfWeek ORDER BY c DESC;","lines":[0.219,0.598,0.232,0.2732971834018944],"version":"v0.7.21-nightly","xAxis":["min","max","median","mean"]},{"title":"Q3","sql":"SELECT Origin, count(*) AS c FROM default.ontime WHERE DepDelay\u003e10 AND Year \u003e= 2000 AND Year \u003c= 2008 GROUP BY Origin ORDER BY c DESC LIMIT 10;","lines":[0.286,0.323,0.298,0.30143179701757133],"version":"v0.7.21-nightly","xAxis":["min","max","median","mean"]},{"title":"Q4","sql":"SELECT IATA_CODE_Reporting_Airline AS Carrier, count() FROM default.ontime WHERE DepDelay\u003e10 AND Year = 2007 GROUP BY Carrier ORDER BY count() DESC;","lines":[0.094,0.134,0.1235,0.1211609725523434],"version":"v0.7.21-nightly","xAxis":["min","max","median","mean"]},{"title":"Q5","sql":"SELECT IATA_CODE_Reporting_Airline AS Carrier, avg(cast(DepDelay\u003e10 as Int8))*1000 AS c3 FROM default.ontime WHERE Year=2007 GROUP BY Carrier ORDER BY c3 DESC;","lines":[0.115,0.318,0.1405,0.1472753618668544],"version":"v0.7.21-nightly","xAxis":["min","max","median","mean"]},{"title":"Q6","sql":"SELECT IATA_CODE_Reporting_Airline AS Carrier, avg(cast(DepDelay\u003e10 as Int8))*1000 AS c3 FROM default.ontime WHERE Year\u003e=2000 AND Year \u003c=2008 GROUP BY Carrier ORDER BY c3 DESC;","lines":[0.332,0.364,0.3445,0.34497570674141576],"version":"v0.7.21-nightly","xAxis":["min","max","median","mean"]},{"title":"Q7","sql":"SELECT IATA_CODE_Reporting_Airline AS Carrier, avg(DepDelay) * 1000 AS c3 FROM default.ontime WHERE Year \u003e= 2000 AND Year \u003c= 2008 GROUP BY Carrier;","lines":[0.326,0.496,0.34,0.3519595255718442],"version":"v0.7.21-nightly","xAxis":["min","max","median","mean"]},{"title":"Q8","sql":"SELECT Year, avg(DepDelay) FROM default.ontime GROUP BY Year;","lines":[0.437,0.562,0.4625,0.477229309514892],"version":"v0.7.21-nightly","xAxis":["min","max","median","mean"]},{"title":"Q9","sql":"SELECT Year, count(*) as c1 FROM default.ontime GROUP BY Year;","lines":[0.273,0.407,0.2895,0.3021027327610153],"version":"v0.7.21-nightly","xAxis":["min","max","median","mean"]},{"title":"Q10","sql":"SELECT avg(cnt) FROM (SELECT Year,Month,count(*) AS cnt FROM default.ontime WHERE DepDel15=1 GROUP BY Year,Month) a;","lines":[0.395,0.474,0.409,0.41756446010543646],"version":"v0.7.21-nightly","xAxis":["min","max","median","mean"]},{"title":"Q11","sql":"SELECT avg(c1) FROM (SELECT Year,Month,count(*) AS c1 FROM default.ontime GROUP BY Year,Month) a;","lines":[0.374,0.457,0.3865,0.3923124836746533],"version":"v0.7.21-nightly","xAxis":["min","max","median","mean"]},{"title":"Q12","sql":"SELECT OriginCityName, DestCityName, count(*) AS c FROM default.ontime GROUP BY OriginCityName, DestCityName ORDER BY c DESC LIMIT 10;","lines":[2.67,2.716,2.691,2.691162537265576],"version":"v0.7.21-nightly","xAxis":["min","max","median","mean"]},{"title":"Q13","sql":"SELECT OriginCityName, count(*) AS c FROM default.ontime GROUP BY OriginCityName ORDER BY c DESC LIMIT 10;","lines":[1.041,1.059,1.053,1.0505837704526235],"version":"v0.7.21-nightly","xAxis":["min","max","median","mean"]},{"title":"Q14","sql":"SELECT count(*) FROM default.ontime;","lines":[0.007,0.039,0.009,0.01065809679964007],"version":"v0.7.21-nightly","xAxis":["min","max","median","mean"]}]}